biapol_utilities/__init__.py
biapol_utilities/data/__init__.py
biapol_utilities/data/_data.py
biapol_utilities/label/__init__.py
biapol_utilities/label/_compare_labels.py
biapol_utilities/label/_filter_similarity_matrix.py
biapol_utilities/label/_intersection_over_union.py
biapol_utilities/label/_match_labels.py
biapol_utilities/label/_matching_algorithms.py
biapol_utilities/utilities/__init__.py
biapol_utilities/utilities/_list_utilities.py
biapol_utilities-0.0.3.dist-info/LICENSE
biapol_utilities-0.0.3.dist-info/METADATA
biapol_utilities-0.0.3.dist-info/WHEEL
biapol_utilities-0.0.3.dist-info/top_level.txt
biapol_utilities-0.0.3.dist-info/RECORD
