Metadata-Version: 2.1
Name: biapol-utilities
Version: 0.0.3
Summary: Collection of bio-image analysis functions of the biapol group @ TU Dresden.
Home-page: https://github.com/BiAPoL/biapol-utilities.git
Author: Johannes Müller, Robert Haase
Author-email: johannes_richard.mueller@tu-dresden.de
License: BSD-3-Clause
Platform: UNKNOWN
Classifier: Development Status :: 2 - Pre-Alpha
Classifier: Intended Audience :: Developers
Classifier: Topic :: Software Development :: Testing
Classifier: Programming Language :: Python
Classifier: Programming Language :: Python :: 3
Classifier: Programming Language :: Python :: 3.7
Classifier: Programming Language :: Python :: 3.8
Classifier: Programming Language :: Python :: 3.9
Classifier: Operating System :: OS Independent
Classifier: License :: OSI Approved :: BSD License
Requires-Python: >=3.7
License-File: LICENSE
Requires-Dist: numpy
Requires-Dist: scikit-image
Requires-Dist: scikit-learn
Requires-Dist: pandas
Requires-Dist: matplotlib
